insta_webhook_utils_modernization/S3StorageManager.cp311-win_amd64.pyd
insta_webhook_utils_modernization/S3StorageManager.py
insta_webhook_utils_modernization/__init__.py
insta_webhook_utils_modernization/common_functions.cp311-win_amd64.pyd
insta_webhook_utils_modernization/common_functions.py
insta_webhook_utils_modernization/indentifier_code.cp311-win_amd64.pyd
insta_webhook_utils_modernization/indentifier_code.py
insta_webhook_utils_modernization/insta_api_builder.cp311-win_amd64.pyd
insta_webhook_utils_modernization/insta_api_builder.py
insta_webhook_utils_modernization/parent_post_handler_functions.cp311-win_amd64.pyd
insta_webhook_utils_modernization/parent_post_handler_functions.py
insta_webhook_utils_modernization/raw_model_mapper.cp311-win_amd64.pyd
insta_webhook_utils_modernization/raw_model_mapper.py
insta_webhook_utils_modernization/rules_object_for_parent_post.cp311-win_amd64.pyd
insta_webhook_utils_modernization/rules_object_for_parent_post.py
insta_webhook_utils_modernization/rules_objects_for_comments.cp311-win_amd64.pyd
insta_webhook_utils_modernization/rules_objects_for_comments.py
insta_webhook_utils_modernization/setting_modification.cp311-win_amd64.pyd
insta_webhook_utils_modernization/setting_modification.py
insta_webhook_utils_modernization-0.4.7.dist-info/METADATA
insta_webhook_utils_modernization-0.4.7.dist-info/WHEEL
insta_webhook_utils_modernization-0.4.7.dist-info/top_level.txt
insta_webhook_utils_modernization-0.4.7.dist-info/RECORD
