Metadata-Version: 2.1
Name: insta_webhook_utils_modernization
Version: 0.4.7
Summary: This package contains the utility functions for Instagram Webhook
Home-page: https://github.com/LocoBuzz-Solutions-Pvt-Ltd/insta_webhook_utils_modernization
Author: Sheikh Muhammed Shoaib
Author-email: shoaib.sheikh@locobuzz.com
Classifier: Programming Language :: Python :: 3
Classifier: License :: OSI Approved :: MIT License
Classifier: Operating System :: OS Independent
Requires-Python: >=3.11
Requires-Dist: Cython
Requires-Dist: jsonschema
Requires-Dist: pytz
Requires-Dist: requests
Requires-Dist: aiohttp
Requires-Dist: boto3
